langchain_b12/__init__.py
langchain_b12/py.typed
langchain_b12/citations/citations.py
langchain_b12/genai/embeddings.py
langchain_b12/genai/genai.py
langchain_b12/genai/genai_utils.py
langchain_b12-0.1.8.dist-info/METADATA
langchain_b12-0.1.8.dist-info/WHEEL
langchain_b12-0.1.8.dist-info/RECORD
