Metadata-Version: 2.4
Name: langchain-b12
Version: 0.1.8
Summary: A reusable collection of tools and implementations for Langchain
Author-email: Vincent Min <vincent.min@b12-consulting.com>
Requires-Python: >=3.11
Requires-Dist: langchain-core>=0.3.60
